hygiene/__init__.py
hygiene/singleton.py
hygiene/payload/__init__.py
hygiene/payload/boxing/__init__.py
hygiene/payload/boxing/boxing.py
hygiene/tests/test.py
hygiene/util/__init__.py
hygiene/util/builders/__init__.py
hygiene/util/builders/csv.py
hygiene/util/common/__init__.py
hygiene/util/common/helpers/__init__.py
hygiene/util/common/helpers/_csv.py
hygiene/util/formatters/__init__.py
hygiene/util/formatters/single/__init__.py
hygiene/util/formatters/single/csv.py
hygiene/util/formatters/single/json.py
hygiene/util/formatters/single/yaml.py
llm_hygiene-0.0.1.dist-info/LICENSE
llm_hygiene-0.0.1.dist-info/METADATA
llm_hygiene-0.0.1.dist-info/WHEEL
llm_hygiene-0.0.1.dist-info/top_level.txt
llm_hygiene-0.0.1.dist-info/RECORD
